{
	"$schema": "https://schema.management.azure.com/schemas/2015-01-01/deploymentParameters.json#",
	"contentVersion": "1.0.0.0",
	"parameters": {
		"factoryName": {
			"value": "adf-netflix-sunim"
		},
		"datalake_connection_accountKey": {
			"value": ""
		},
		"datalake_connection_properties_typeProperties_url": {
			"value": "https://netflixprojectdatalake.dfs.core.windows.net/"
		},
		"githubconnection_properties_typeProperties_url": {
			"value": "https://raw.githubusercontent.com/"
		},
		"containerUri": {
			"value": ""
		},
		"containerSasToken": {
			"value": ""
		}
	}
}